plasann/__init__.py
plasann/annotate.py
plasann/blast_search.py
plasann/database_download.py
plasann/draw_plasmid.py
plasann/essential_annotation.py
plasann-1.1.6.dist-info/licenses/LICENSE
plasann-1.1.6.dist-info/METADATA
plasann-1.1.6.dist-info/WHEEL
plasann-1.1.6.dist-info/entry_points.txt
plasann-1.1.6.dist-info/top_level.txt
plasann-1.1.6.dist-info/RECORD
